adnuntius/__init__.py
adnuntius/api.py
adnuntius/compare_json.py
adnuntius/util.py
adnuntius-1.25.0.dist-info/licenses/LICENSE.txt
adnuntius-1.25.0.dist-info/METADATA
adnuntius-1.25.0.dist-info/WHEEL
adnuntius-1.25.0.dist-info/top_level.txt
adnuntius-1.25.0.dist-info/RECORD
