Metadata-Version: 2.4
Name: adnuntius
Version: 1.25.0
Summary: Interface and tools for using the Adnuntius API
Home-page: https://github.com/Adnuntius/api-tools
Author: Adnuntius
Author-email: tech@adnuntius.com
License: MIT
Classifier: License :: OSI Approved :: MIT License
Classifier: Programming Language :: Python :: 3
Classifier: Programming Language :: Python :: 3.8
License-File: LICENSE.txt
Requires-Dist: python-dateutil>=2.8
Requires-Dist: requests>=2.22
Requires-Dist: requests_toolbelt>=0.9
Dynamic: author
Dynamic: author-email
Dynamic: classifier
Dynamic: description
Dynamic: home-page
Dynamic: license
Dynamic: license-file
Dynamic: requires-dist
Dynamic: summary
